word_document_table_editor/__init__.py
word_document_table_editor/main.py
word_document_table_editor/tools.py
word_document_table_editor/utils.py
word_document_table_editor_mcp-1.0.4.dist-info/METADATA
word_document_table_editor_mcp-1.0.4.dist-info/WHEEL
word_document_table_editor_mcp-1.0.4.dist-info/entry_points.txt
word_document_table_editor_mcp-1.0.4.dist-info/top_level.txt
word_document_table_editor_mcp-1.0.4.dist-info/RECORD
